agency_swarm/__init__.py
agency_swarm/context.py
agency_swarm/hooks.py
agency_swarm/agency/__init__.py
agency_swarm/agency/completions.py
agency_swarm/agency/core.py
agency_swarm/agency/helpers.py
agency_swarm/agency/responses.py
agency_swarm/agency/setup.py
agency_swarm/agency/visualization.py
agency_swarm/agent/__init__.py
agency_swarm/agent/agent_flow.py
agency_swarm/agent/attachment_manager.py
agency_swarm/agent/constants.py
agency_swarm/agent/context_types.py
agency_swarm/agent/core.py
agency_swarm/agent/execution.py
agency_swarm/agent/execution_guardrails.py
agency_swarm/agent/execution_helpers.py
agency_swarm/agent/execution_streaming.py
agency_swarm/agent/file_manager.py
agency_swarm/agent/initialization.py
agency_swarm/agent/subagents.py
agency_swarm/agent/tools.py
agency_swarm/cli/__init__.py
agency_swarm/cli/main.py
agency_swarm/cli/migrate_agent.py
agency_swarm/cli/utils/__init__.py
agency_swarm/cli/utils/generate-agent-from-settings.ts
agency_swarm/integrations/fastapi.py
agency_swarm/integrations/mcp_server.py
agency_swarm/integrations/fastapi_utils/endpoint_handlers.py
agency_swarm/integrations/fastapi_utils/file_handler.py
agency_swarm/integrations/fastapi_utils/logging_middleware.py
agency_swarm/integrations/fastapi_utils/request_models.py
agency_swarm/messages/__init__.py
agency_swarm/messages/message_filter.py
agency_swarm/messages/message_formatter.py
agency_swarm/streaming/__init__.py
agency_swarm/streaming/utils.py
agency_swarm/tools/__init__.py
agency_swarm/tools/base_tool.py
agency_swarm/tools/concurrency.py
agency_swarm/tools/mcp_manager.py
agency_swarm/tools/send_message.py
agency_swarm/tools/tool_factory.py
agency_swarm/tools/utils.py
agency_swarm/ui/__init__.py
agency_swarm/ui/core/agui_adapter.py
agency_swarm/ui/core/console_event_adapter.py
agency_swarm/ui/core/layout_algorithms.py
agency_swarm/ui/demos/compact.py
agency_swarm/ui/demos/copilot.py
agency_swarm/ui/demos/launcher.py
agency_swarm/ui/demos/persistence.py
agentswarm-1.0.3.dist-info/METADATA
agentswarm-1.0.3.dist-info/WHEEL
agentswarm-1.0.3.dist-info/entry_points.txt
agentswarm-1.0.3.dist-info/licenses/LICENSE
agentswarm-1.0.3.dist-info/RECORD
